libinephany/__init__.py
libinephany/aws/__init__.py
libinephany/aws/s3_functions.py
libinephany/observations/__init__.py
libinephany/observations/observation_utils.py
libinephany/observations/observer_pipeline.py
libinephany/observations/pipeline_coordinator.py
libinephany/observations/statistic_manager.py
libinephany/observations/statistic_trackers.py
libinephany/observations/observers/__init__.py
libinephany/observations/observers/base_observers.py
libinephany/observations/observers/local_observers.py
libinephany/observations/observers/observer_containers.py
libinephany/observations/observers/global_observers/__init__.py
libinephany/observations/observers/global_observers/base_classes.py
libinephany/observations/observers/global_observers/constants.py
libinephany/observations/observers/global_observers/gradient_observers.py
libinephany/observations/observers/global_observers/hyperparameter_observers.py
libinephany/observations/observers/global_observers/loss_observers.py
libinephany/observations/observers/global_observers/model_observers.py
libinephany/observations/observers/global_observers/progress_observers.py
libinephany/observations/post_processors/__init__.py
libinephany/observations/post_processors/postprocessors.py
libinephany/pydantic_models/__init__.py
libinephany/pydantic_models/configs/__init__.py
libinephany/pydantic_models/configs/hyperparameter_configs.py
libinephany/pydantic_models/configs/observer_config.py
libinephany/pydantic_models/configs/outer_model_config.py
libinephany/pydantic_models/schemas/__init__.py
libinephany/pydantic_models/schemas/agent_info.py
libinephany/pydantic_models/schemas/inner_task_profile.py
libinephany/pydantic_models/schemas/observation_models.py
libinephany/pydantic_models/schemas/request_schemas.py
libinephany/pydantic_models/schemas/response_schemas.py
libinephany/pydantic_models/schemas/tensor_statistics.py
libinephany/pydantic_models/states/__init__.py
libinephany/pydantic_models/states/hyperparameter_states.py
libinephany-1.1.33.dist-info/licenses/LICENSE
libinephany-1.1.33.dist-info/METADATA
libinephany-1.1.33.dist-info/WHEEL
libinephany-1.1.33.dist-info/top_level.txt
libinephany-1.1.33.dist-info/RECORD
