Metadata-Version: 2.4
Name: libinephany
Version: 1.1.33
Summary: Inephany library containing code commonly used by multiple subpackages.
Author-email: Inephany <info@inephany.com>
License: Apache 2.0
Keywords: libinephany,library,utilities
Classifier: Development Status :: 4 - Beta
Classifier: Intended Audience :: Developers
Classifier: Programming Language :: Python :: 3
Classifier: Programming Language :: Python :: 3.10
Classifier: Programming Language :: Python :: 3.11
Classifier: Programming Language :: Python :: 3.12
Requires-Python: >=3.10
License-File: LICENSE
Requires-Dist: pydantic<3.0.0,>=2.5.0
Requires-Dist: loguru<0.8.0,>=0.7.0
Requires-Dist: requests<3.0.0,>=2.28.0
Requires-Dist: numpy<2.0.0,>=1.24.0
Requires-Dist: scipy<2.0.0,>=1.10.0
Requires-Dist: slack-sdk<4.0.0,>=3.20.0
Requires-Dist: boto3<2.0.0,>=1.26.0
Requires-Dist: fastapi<0.116.0,>=0.100.0
Requires-Dist: aiohttp<4.0.0,>=3.8.0
Requires-Dist: torch<2.9.0,>=2.1.0
Requires-Dist: transformers<4.58.0,>=4.51.0
Requires-Dist: pandas<3.0.0,>=2.0.0
Requires-Dist: accelerate<2.0.0,>=0.20.0
Requires-Dist: gymnasium<2.0.0,>=0.29.0
Provides-Extra: dev
Requires-Dist: pytest<9.0.0,>=7.0.0; extra == "dev"
Requires-Dist: pytest-mock<4.0.0,>=3.10.0; extra == "dev"
Requires-Dist: pytest-asyncio<0.26.0,>=0.21.0; extra == "dev"
Requires-Dist: bump-my-version==0.11.0; extra == "dev"
Requires-Dist: black==24.4.2; extra == "dev"
Requires-Dist: isort==5.9.3; extra == "dev"
Requires-Dist: flake8==7.1.0; extra == "dev"
Requires-Dist: pre-commit==4.0.1; extra == "dev"
Requires-Dist: mypy==1.13.0; extra == "dev"
Requires-Dist: types-PyYAML==6.0.12.20240808; extra == "dev"
Requires-Dist: typeguard==4.3.0; extra == "dev"
Dynamic: license-file
